app/__init__.py
povideo/__init__.py
povideo/api/__init__.py
povideo/api/video.py
povideo/core/VideoType.py
povideo/core/__init__.py
povideo/lib/__init__.py
povideo/lib/tencent/__init__.py
povideo/lib/tencent/audio2txt_service.py
tests/__init__.py
tests/test_video.py
povideo-0.0.8.dist-info/LICENSE
povideo-0.0.8.dist-info/METADATA
povideo-0.0.8.dist-info/WHEEL
povideo-0.0.8.dist-info/top_level.txt
povideo-0.0.8.dist-info/RECORD
