Metadata-Version: 2.1
Name: povideo
Version: 0.0.8
Summary: pip install povideo
Home-page: https://www.python-office.com/
Author: CoderWanFeng
Author-email: 1957875073@qq.com
License: MIT
Project-URL: Bug Tracker, https://github.com/CoderWanFeng/povideo/issues
Project-URL: Documentation, https://github.com/CoderWanFeng/povideo/blob/master/README.md
Project-URL: Source Code, https://github.com/CoderWanFeng/povideo
Platform: any
Requires-Python: >=3.7
License-File: LICENSE
Requires-Dist: moviepy
Requires-Dist: tencentcloud-sdk-python
Requires-Dist: pyttsx3
Requires-Dist: pofile
